eolas_mech_mcp/__init__.py
eolas_mech_mcp/__main__.py
eolas_mech_mcp/server.py
eolas_mech_mcp/server_instance.py
eolas_mech_mcp/tools/__init__.py
eolas_mech_mcp/tools/add.py
eolas_mech_mcp/tools/top_up.py
eolas_mech_mcp/utils/__init__.py
eolas_mech_mcp/utils/wallet.py
eolas_mech_mcp-1.0.16.dist-info/METADATA
eolas_mech_mcp-1.0.16.dist-info/WHEEL
eolas_mech_mcp-1.0.16.dist-info/entry_points.txt
eolas_mech_mcp-1.0.16.dist-info/top_level.txt
eolas_mech_mcp-1.0.16.dist-info/RECORD
