Metadata-Version: 2.4
Name: eolas-mech-mcp
Version: 1.0.16
Summary: A Model Context Protocol (MCP) server for wallet and computation tools.
Author-email: Eolas <nicflamel0x@gmail.com>
Project-URL: Homepage, https://mcp.eolas.fun/
Classifier: Programming Language :: Python :: 3
Classifier: License :: OSI Approved :: MIT License
Classifier: Operating System :: OS Independent
Requires-Python: >=3.10
Requires-Dist: mcp[cli]
Requires-Dist: pydantic
Requires-Dist: pycryptodome
Requires-Dist: web3
Requires-Dist: python-dotenv
